coppeliasim_zmqremoteapi_client/__init__.py
coppeliasim_zmqremoteapi_client/asyncio/__init__.py
coppeliasim_zmqremoteapi_client-2.0.0.dist-info/METADATA
coppeliasim_zmqremoteapi_client-2.0.0.dist-info/WHEEL
coppeliasim_zmqremoteapi_client-2.0.0.dist-info/licenses/LICENSE
coppeliasim_zmqremoteapi_client-2.0.0.dist-info/RECORD
